Workbook

Sheet Column Relations Sheet
B1: Summary Sheet - templete column names | C1: Noon KSA column name | D1: Remarks | E1: Amazon KSA Colum Name | F1: Remarks
B2: Channel | C2: Contract | D2: if the contract is MPABANGBKLSA, & document type is Invoice then it should be buckated as noon KSA. if the contract is MPABANGBKLSA, & document type is credit note then it should be buckated as noon KSA return | E2: Sales Channel | F2: If sales channel is amazon.sa it should consider Amazon KSA
B3: Date | C3: Document Date | F3: Payments Date
B4: Day | D4: it should autometically take the day number from date itslef | F4: it should autometically take the day number from date itslef
B5: Month | D5: it should autometically take the Month from date itslef | F5: it should autometically take the Month from date itslef
B6: Year | D6: it should autometically take the year from date itslef | F6: it should autometically take the year from date itslef
B7: Order Number | C7: Source Doc Line Nr | E7: Amazon Order Id
B8: Zoho SKU | D8: Currently mark it "NA" | F8: Currently mark it "NA"
B9: QTY | C9: Invoice Line Nr | E9: Shipped Quantity
B10: Category | D10: linked with description check Summary Sheet - templete and create category according to description as per the reference | F10: linked with description check Summary Sheet - templete and create category according to description as per the reference
B11: Channel SKU | C11: SKU | E11: Merchant SKU
B12: Channel Item Name | C12: Description | E12: Title
B13: Value (Including VAT) | D13: multiply Price Including VAT (Document Currency) with quantiy for respective order id | F13: multiply Item Price with quantiy for respective order id

Sheet Summary Sheet - templete
A1: Channel | B1: Date | C1: Day | D1: Month | E1: Year | F1: Order Number | G1: checK | H1: Zoho SKU | I1: QTY | J1: Category | K1: Channel SKU | L1: Channel Item Name | M1: Value (Including VAT)
A2: Noon KSA | B2: 46018 | C2: 27 | D2: 46016 | E2: 2025 | F2: NSAHC0037327791-4-P1 | G2: =VLOOKUP(F2,'Noon KSA'!O:O,1,0) -> NSAHC0037327791-4-P1 | H2: NA | I2: 1 | J2: Tablet | K2: N70210253V-1 | L2: Renewed - Ipad 2019 (7th Gen) 10.2-Inch 128GB Wi-Fi,LTE, Space Gray - International Version | M2: 699
A3: Noon KSA | B3: 46018 | C3: 27 | D3: 46016 | E3: 2025 | F3: NSAHC0063312130-2-P1 | G3: =VLOOKUP(F3,'Noon KSA'!O:O,1,0) -> NSAHC0063312130-2-P1 | H3: NA | I3: 1 | J3: Tablet | K3: N70210253V-1 | L3: Renewed - Ipad 2019 (7th Gen) 10.2-Inch 128GB Wi-Fi,LTE, Space Gray - International Version | M3: 599
A4: Amazon KSA | B4: 46018 | C4: 27 | D4: 46016 | E4: 2025 | F4: 408-5178714-0670729 | G4: =VLOOKUP(F4,'Amazon KSA'!A:A,1,0) -> 408-5178714-0670729 | H4: NA | I4: 1 | J4: Smartphone | K4: 93-PZWP-1Y65 | L4: Apple (Refurbished) iPhone 14 Pro Max 5G 128GB - Deep Purple | M4: 2167
A5: Noon KSA | B5: 46019 | C5: 28 | D5: 46016 | E5: 2025 | F5: NSAHC0082186765-2-P1 | G5: =VLOOKUP(F5,'Noon KSA'!O:O,1,0) -> NSAHC0082186765-2-P1 | H5: NA | I5: 1 | J5: Tablet | K5: N70210253V-1 | L5: Renewed - Ipad 2019 (7th Gen) 10.2-Inch 128GB Wi-Fi,LTE, Space Gray - International Version | M5: 699
A6: Noon KSA | B6: 46019 | C6: 28 | D6: 46016 | E6: 2025 | F6: NSAHC0065081485-3-P1 | G6: =VLOOKUP(F6,'Noon KSA'!O:O,1,0) -> NSAHC0065081485-3-P1 | H6: NA | I6: 1 | J6: Tablet | K6: N53408690A | L6: Renewed - iPad Air 2 9.7inch 32GB Wi-Fi Space Gray With FaceTime | M6: 399
A7: Noon KSA | B7: 46019 | C7: 28 | D7: 46016 | E7: 2025 | F7: NSAHC0010472664-1-P1 | G7: =VLOOKUP(F7,'Noon KSA'!O:O,1,0) -> NSAHC0010472664-1-P1 | H7: NA | I7: 1 | J7: Tablet | K7: N34261427A | L7: Renewed - iPad 2017 (5th Gen) 9.7inch 32GBWiFi Space Gray With Facetime | M7: 429
A8: Noon KSA | B8: 46019 | C8: 28 | D8: 46016 | E8: 2025 | F8: NSAHC0064138549-1-P1 | G8: =VLOOKUP(F8,'Noon KSA'!O:O,1,0) -> NSAHC0064138549-1-P1 | H8: NA | I8: 1 | J8: Tablet | K8: N34261427A | L8: Renewed - iPad 2017 (5th Gen) 9.7inch 32GBWiFi Space Gray With Facetime | M8: 429
A9: Noon KSA | B9: 46019 | C9: 28 | D9: 46016 | E9: 2025 | F9: NSAHC0080314615-1-P1 | G9: =VLOOKUP(F9,'Noon KSA'!O:O,1,0) -> NSAHC0080314615-1-P1 | H9: NA | I9: 1 | J9: Tablet | K9: N53408690A | L9: Renewed - iPad Air 2 9.7inch 32GB Wi-Fi Space Gray With FaceTime | M9: 399
A10: Noon KSA | B10: 46020 | C10: 29 | D10: 46016 | E10: 2025 | F10: NSAHC0007179996-2-P1 | G10: =VLOOKUP(F10,'Noon KSA'!O:O,1,0) -> NSAHC0007179996-2-P1 | H10: NA | I10: 1 | J10: Tablet | K10: N70210242V-1 | L10: Renewed - iPad Pro 2021 5th Generation 12.9-Inch, M1 Chip, 512GB, Wi-Fi, 5G, Silver with Facetime - International Specs | M10: 3189
A11: Noon KSA | B11: 46020 | C11: 29 | D11: 46016 | E11: 2025 | F11: NSAHC0088492440-1-P1 | G11: =VLOOKUP(F11,'Noon KSA'!O:O,1,0) -> NSAHC0088492440-1-P1 | H11: NA | I11: 1 | J11: Tablet | K11: N50388287A | L11: Renewed - iPad-2019 (7th Gen) 10.2inch 32GB Wi-Fi 4G LTE Silver - International Version | M11: 524
A12: Noon KSA | B12: 46020 | C12: 29 | D12: 46016 | E12: 2025 | F12: NSAHC0084762122-1-P1 | G12: =VLOOKUP(F12,'Noon KSA'!O:O,1,0) -> NSAHC0084762122-1-P1 | H12: NA | I12: 1 | J12: Tablet | K12: N34261427A | L12: Renewed - iPad 2017 (5th Gen) 9.7inch 32GBWiFi Space Gray With Facetime | M12: 429
A13: Noon KSA | B13: 46020 | C13: 29 | D13: 46016 | E13: 2025 | F13: NSAHC0084762122-2-P1 | G13: =VLOOKUP(F13,'Noon KSA'!O:O,1,0) -> NSAHC0084762122-2-P1 | H13: NA | I13: 2 | J13: Tablet | K13: N53382311A | L13: Renewed - iPad 2018 (6th Gen) 9.7-Inch 32GB Wi-Fi Space Grey - International Version | M13: 398
A14: Noon KSA | B14: 46020 | C14: 29 | D14: 46016 | E14: 2025 | F14: NSAHC0085871396-1-P1 | G14: =VLOOKUP(F14,'Noon KSA'!O:O,1,0) -> NSAHC0085871396-1-P1 | H14: NA | I14: 1 | J14: Tablet | K14: N70259511V-1 | L14: Renewed – iPad Pro 11-Inch (2018) 1st Gen WiFi + Cellular 256GB Space Gray | M14: 1649
A15: Noon KSA | B15: 46020 | C15: 29 | D15: 46016 | E15: 2025 | F15: NSAHC0002594656-2-P1 | G15: =VLOOKUP(F15,'Noon KSA'!O:O,1,0) -> NSAHC0002594656-2-P1 | H15: NA | I15: 1 | J15: Tablet | K15: N53382311A | L15: Renewed - iPad 2018 (6th Gen) 9.7-Inch 32GB Wi-Fi Space Grey - International Version | M15: 398
A16: Noon KSA | B16: 46020 | C16: 29 | D16: 46016 | E16: 2025 | F16: NSAHC0047546591-1-P1 | G16: =VLOOKUP(F16,'Noon KSA'!O:O,1,0) -> NSAHC0047546591-1-P1 | H16: NA | I16: 1 | J16: Tablet | K16: N53382311A | L16: Renewed - iPad 2018 (6th Gen) 9.7-Inch 32GB Wi-Fi Space Grey - International Version | M16: 398
... A19: Noon KSA Return | B19: 46020 | C19: 29 | D19: 46016 | E19: 2025 | F19: NSAHC0091664187-1-P1 | G19: =VLOOKUP(F19,'Noon KSA'!O:O,1,0) -> NSAHC0091664187-1-P1 | H19: NA | I19: -1 | J19: Smartphone | K19: N70095753V-1 | L19: Renewed - iPhone 14 Pro Max 128GB Deep Purple 5G With Facetime | M19: -2399
A20: Amazon KSA | B20: 46020 | C20: 29 | D20: 46016 | E20: 2025 | F20: 405-4010753-1240312 | G20: =VLOOKUP(F20,'Amazon KSA'!A:A,1,0) -> 405-4010753-1240312 | H20: NA | I20: 1 | J20: Smartphone | K20: 93-PZWP-1Y65 | L20: Apple (Refurbished) iPhone 14 Pro Max 5G 128GB - Deep Purple | M20: 2098
A21: Amazon KSA | B21: 46020 | C21: 29 | D21: 46016 | E21: 2025 | F21: 405-3980961-9785131 | G21: =VLOOKUP(F21,'Amazon KSA'!A:A,1,0) -> 405-3980961-9785131 | H21: NA | I21: 1 | J21: Smartphone | K21: TY-BWW6-X94D | L21: Apple (Refurbished) iPhone 14 Plus 5G 128GB - Midnight | M21: 1776
A22: Noon KSA | B22: 46021 | C22: 30 | D22: 46016 | E22: 2025 | F22: NSAHC0017132006-2-P1 | G22: =VLOOKUP(F22,'Noon KSA'!O:O,1,0) -> NSAHC0017132006-2-P1 | H22: NA | I22: 1 | J22: Tablet | K22: N50388287A | L22: Renewed - iPad-2019 (7th Gen) 10.2inch 32GB Wi-Fi 4G LTE Silver - International Version | M22: 524
A23: Noon KSA | B23: 46022 | C23: 31 | D23: 46016 | E23: 2025 | F23: NSAHC0013207023-1-P1 | G23: =VLOOKUP(F23,'Noon KSA'!O:O,1,0) -> NSAHC0013207023-1-P1 | H23: NA | I23: 1 | J23: Tablet | K23: N53382311A | L23: Renewed - iPad 2018 (6th Gen) 9.7-Inch 32GB Wi-Fi Space Grey - International Version | M23: 398
A24: Noon KSA | B24: 46022 | C24: 31 | D24: 46016 | E24: 2025 | F24: NSAHC0053527539-1-P1 | G24: =VLOOKUP(F24,'Noon KSA'!O:O,1,0) -> NSAHC0053527539-1-P1 | H24: NA | I24: 1 | J24: Tablet | K24: N51142274A | L24: Renewed - iPad Pro 2020 (4th Gen) 12.9-inch 512GB Wi-Fi 4G LTE Space Gray With FaceTime | M24: 2599
A25: Noon KSA | B25: 46023 | C25: 1 | D25: 46048 | E25: 2026 | F25: NSAHC0047226333-2-P1 | G25: =VLOOKUP(F25,'Noon KSA'!O:O,1,0) -> NSAHC0047226333-2-P1 | H25: NA | I25: 1 | J25: Tablet | K25: N70262377V-1 | L25: Renewed - iPad Pro 2016 (1st Gen) 9.7-Inch 32GB Wi-Fi Space Gray | M25: 499
A26: Noon KSA | B26: 46023 | C26: 1 | D26: 46048 | E26: 2026 | F26: NSAHC0083560251-1-P1 | G26: =VLOOKUP(F26,'Noon KSA'!O:O,1,0) -> NSAHC0083560251-1-P1 | H26: NA | I26: 1 | J26: Tablet | K26: N70262377V-1 | L26: Renewed - iPad Pro 2016 (1st Gen) 9.7-Inch 32GB Wi-Fi Space Gray | M26: 499
A27: Noon KSA | B27: 46023 | C27: 1 | D27: 46048 | E27: 2026 | F27: NSAHC0047023168-1-P1 | G27: =VLOOKUP(F27,'Noon KSA'!O:O,1,0) -> NSAHC0047023168-1-P1 | H27: NA | I27: 1 | J27: Tablet | K27: N70262333V-1 | L27: Renewed - iPad Pro 2016 (1st Gen) 9.7-Inch 32GB WiFi Silver | M27: 449
A28: Noon KSA | B28: 46023 | C28: 1 | D28: 46048 | E28: 2026 | F28: NSAHC0001494244-1-P1 | G28: =VLOOKUP(F28,'Noon KSA'!O:O,1,0) -> NSAHC0001494244-1-P1 | H28: NA | I28: 1 | J28: Smartphone | K28: N70095753V-1 | L28: Renewed - iPhone 14 Pro Max 128GB Deep Purple 5G With Facetime | M28: 2298
A29: Noon KSA | B29: 46023 | C29: 1 | D29: 46048 | E29: 2026 | F29: NSAHC0000707946-1-P1 | G29: =VLOOKUP(F29,'Noon KSA'!O:O,1,0) -> NSAHC0000707946-1-P1 | H29: NA | I29: 1 | J29: Smartphone | K29: N53431294A | L29: Renewed - iPhone 14 Pro 256GB Deep Purple 5G With Facetime - International Version | M29: 2262
A30: Noon KSA | B30: 46023 | C30: 1 | D30: 46048 | E30: 2026 | F30: NSAHC0082879023-1-P1 | G30: =VLOOKUP(F30,'Noon KSA'!O:O,1,0) -> NSAHC0082879023-1-P1 | H30: NA | I30: 1 | J30: Tablet | K30: N70262333V-1 | L30: Renewed - iPad Pro 2016 (1st Gen) 9.7-Inch 32GB WiFi Silver | M30: 449
A31: Amazon KSA | B31: 46023 | C31: 1 | D31: 46048 | E31: 2026 | F31: 406-8433320-8808338 | G31: =VLOOKUP(F31,'Amazon KSA'!A:A,1,0) -> 406-8433320-8808338 | H31: NA | I31: 1 | J31: Smartphone | K31: K7-J3IC-O2UO | L31: Apple (Refurbished) iPhone 14 Pro 5G 256GB - Deep Purple | M31: 2124
A32: Amazon KSA | B32: 46023 | C32: 1 | D32: 46048 | E32: 2026 | F32: 404-3161102-5796340 | G32: =VLOOKUP(F32,'Amazon KSA'!A:A,1,0) -> 404-3161102-5796340 | H32: NA | I32: 1 | J32: Smartphone | K32: K7-J3IC-O2UO | L32: Apple (Refurbished) iPhone 14 Pro 5G 256GB - Deep Purple | M32: 2124

Sheet Amazon KSA
A1: Amazon Order Id | B1: Merchant Order Id | C1: Shipment ID | D1: Shipment Item Id | E1: Amazon Order Item Id | F1: Merchant Order Item Id | G1: Purchase Date | H1: Payments Date | I1: Shipment Date | J1: Reporting Date | K1: Buyer Email | L1: Buyer Name | M1: Buyer Phone Number | N1: Merchant SKU | O1: Title | P1: Shipped Quantity | Q1: Currency | R1: Item Price | S1: Item Tax | T1: Shipping Price | U1: Shipping Tax | V1: Gift Wrap Price | W1: Gift Wrap Tax | X1: Ship Service Level | Y1: Recipient Name | Z1: Shipping Address 1 | AA1: Shipping Address 2 | AB1: Shipping Address 3 | AC1: Shipping City | AD1: Shipping State | AE1: Shipping Postal Code | AF1: Shipping Country Code | AG1: Shipping Phone Number | AH1: Billing Address 1 | AI1: Billing Address 2 | AJ1: Billing Address 3 | AK1: Billing City | AL1: Billing State | AM1: bill-postal-code | AN1: bill-country | AO1: Item Promo Discount | AP1: Shipment Promo Discount | AQ1: Carrier | AR1: Tracking Number | AS1: Estimated Arrival Date | AT1: FC | AU1: Fulfillment Channel | AV1: Sales Channel
A2: 406-8433320-8808338 | C2: UJ8PKJ2jj | D2: DhT7LQ10Dz0NR | E2: 58853211395122 | G2: 2026-01-01T20:21:23+03:00 | H2: 2026-01-01T21:42:52+03:00 | I2: 2026-01-01T21:42:52+03:00 | J2: 2026-01-02T00:43:05+03:00 | K2: nz6jdk8fc3cmszp@marketplace.amazon.sa | L2: محمود الشافعى | N2: K7-J3IC-O2UO | O2: Apple (Refurbished) iPhone 14 Pro 5G 256GB - Deep Purple | P2: 1 | Q2: SAR | R2: 2124 | S2: 0 | T2: 12 | U2: 0 | V2: 0 | W2: 0 | X2: Standard | Y2: mahmoud shawky | Z2: JBRA6534, Manazel Al Muttaqeen Street | AA2: 6534 Alzagzoog Tower 9 floor 902 | AC2: Jeddah | AD2: Makkah | AE2: -- | AF2: SA | AH2: AL Faisaliah | AI2: beside Dr. Irfan hostpital | AK2: Jeddah | AL2: Makkah | AM2: -- | AN2: SA | AO2: 0 | AP2: -12 | AQ2: AMZSA | AR2: ASA968021680 | AS2: 2026-01-02T20:00:00+03:00 | AT2: JED4 | AU2: AFN | AV2: amazon.sa
A3: 404-3161102-5796340 | C3: UnZq5DVLj | D3: DDVMzY11Dj0KR | E3: 58840085125642 | G3: 2026-01-01T12:49:08+03:00 | H3: 2026-01-01T20:37:51+03:00 | I3: 2026-01-01T20:37:51+03:00 | J3: 2026-01-01T23:38:01+03:00 | K3: 5sgsy2002t3s533@marketplace.amazon.sa | L3: Masud Rana | N3: K7-J3IC-O2UO | O3: Apple (Refurbished) iPhone 14 Pro 5G 256GB - Deep Purple | P3: 1 | Q3: SAR | R3: 2124 | S3: 0 | T3: 12 | U3: 0 | V3: 0 | W3: 0 | X3: Standard | Y3: Masud Rana | Z3: RNSB2474 | AA3: 2474 | AC3: Riyadh | AD3: Riyadh | AE3: -- | AF3: SA | AH3: RNSB2474 | AI3: 2474 | AK3: Riyadh | AL3: Riyadh | AM3: -- | AN3: SA | AO3: 0 | AP3: -12 | AQ3: AMZSA | AR3: ASA967939869 | AS3: 2026-01-03T20:00:00+03:00 | AT3: JED4 | AU3: AFN | AV3: amazon.sa
A4: 405-4010753-1240312 | C4: U3SytsW5j | D4: DRdcGvBcDQ0yR | E4: 58677921993602 | G4: 2025-12-29T19:13:30+03:00 | H4: 2025-12-29T22:51:47+03:00 | I4: 2025-12-29T22:51:47+03:00 | J4: 2025-12-30T01:51:58+03:00 | K4: hlmh5lq8nz65838@marketplace.amazon.sa | L4: Morsy | N4: 93-PZWP-1Y65 | O4: Apple (Refurbished) iPhone 14 Pro Max 5G 128GB - Deep Purple | P4: 1 | Q4: SAR | R4: 2098 | S4: 0 | T4: 12 | U4: 0 | V4: 0 | W4: 0 | X4: Standard | Y4: Morsy | Z4: JESB7467, شارع ابن ابي الوفاء | AA4: 7467.1053 | AC4: جدة | AD4: مكة المكرمة | AE4: -- | AF4: SA | AH4: JESB7467, شارع ابن ابي الوفاء | AI4: 7467.1053 | AK4: جدة | AL4: مكة المكرمة | AM4: -- | AN4: SA | AO4: 0 | AP4: -12 | AQ4: AMZSA | AR4: ASA964843808 | AS4: 2025-12-30T20:00:00+03:00 | AT4: JED4 | AU4: AFN | AV4: amazon.sa
A5: 405-3980961-9785131 | C5: UNh8Tt68j | D5: Ds7v9LMMDY0MR | E5: 58646280692642 | G5: 2025-12-28T17:12:32+03:00 | H5: 2025-12-29T00:46:56+03:00 | I5: 2025-12-29T00:46:56+03:00 | J5: 2025-12-29T03:47:06+03:00 | K5: 50md4qkjzyt5v24@marketplace.amazon.sa | L5: معيوض سالم الثبيتي | N5: TY-BWW6-X94D | O5: Apple (Refurbished) iPhone 14 Plus 5G 128GB - Midnight | P5: 1 | Q5: SAR | R5: 1776 | S5: 0 | T5: 12 | U5: 0 | V5: 0 | W5: 0 | X5: Standard | Y5: معيوض سالم الثبيتي | Z5: TADB3940 | AA5: 3940 3 | AC5: At Taif | AD5: Makkah | AE5: -- | AF5: SA | AH5: TADB3940 | AI5: 3940 3 | AK5: At Taif | AL5: Makkah | AM5: -- | AN5: SA | AO5: 0 | AP5: -12 | AQ5: AMZSA | AR5: ASA963750282 | AS5: 2025-12-29T20:00:00+03:00 | AT5: JED4 | AU5: AFN | AV5: amazon.sa
A6: 408-5178714-0670729 | C6: U6SRgJHHj | D6: DJ5FYkV3DS0XR | E6: 58595593849962 | G6: 2025-12-26T15:32:54+03:00 | H6: 2025-12-27T20:17:50+03:00 | I6: 2025-12-27T20:17:50+03:00 | J6: 2025-12-27T23:18:03+03:00 | K6: 5vv55y5h60628g5@marketplace.amazon.sa | L6: Kaled Abo Ahmad | N6: 93-PZWP-1Y65 | O6: Apple (Refurbished) iPhone 14 Pro Max 5G 128GB - Deep Purple | P6: 1 | Q6: SAR | R6: 2167 | S6: 0 | T6: 4 | U6: 0 | V6: 0 | W6: 0 | X6: Standard | Y6: Kaled Abo Ahmad | Z6: سليمان الراجحي | AA6: 14 | AC6: الطائف | AD6: مكة المكرمة | AE6: -- | AF6: SA | AH6: سليمان الراجحي | AI6: 14 | AK6: الطائف | AL6: مكة المكرمة | AM6: -- | AN6: SA | AO6: 0 | AP6: -4 | AQ6: AMZSA | AR6: ASA962370423 | AS6: 2025-12-28T20:00:00+03:00 | AT6: JED4 | AU6: AFN | AV6: amazon.sa
A7: 171-8527689-7013914 | C7: U35TmslFj | D7: D8fYq6ZlDg0DR | E7: 58586976313522 | G7: 2025-12-26T01:58:09+03:00 | H7: 2025-12-26T10:29:48+03:00 | I7: 2025-12-26T10:29:48+03:00 | J7: 2025-12-26T13:29:58+03:00 | K7: dxzp889b0k2fdpf@marketplace.amazon.sa | L7: محمد سالم | N7: K7-J3IC-O2UO | O7: Apple (Refurbished) iPhone 14 Pro 5G 256GB - Deep Purple | P7: 1 | Q7: SAR | R7: 2207 | S7: 0 | T7: 12 | U7: 0 | V7: 0 | W7: 0 | X7: Standard | Y7: محمد سالم | Z7: شارع الحج | AA7: 2592 | AC7: مكة المكرمة | AD7: مكة المكرمة | AE7: MFTA2592 | AF7: SA | AH7: شارع الحج | AI7: 2592 | AK7: مكة المكرمة | AL7: مكة المكرمة | AM7: MFTA2592 | AN7: SA | AO7: 0 | AP7: -12 | AQ7: AMZSA | AR7: ASA960928156 | AS7: 2025-12-27T20:00:00+03:00 | AT7: JED4 | AU7: AFN | AV7: amazon.sa
A8: 171-4338663-5400319 | C8: UN9HKPldj | D8: Dj9nqjZJD20KR | E8: 58585564971882 | G8: 2025-12-26T03:03:23+03:00 | H8: 2025-12-26T10:24:46+03:00 | I8: 2025-12-26T10:24:46+03:00 | J8: 2025-12-26T13:24:57+03:00 | K8: 4t54249dkymcxny@marketplace.amazon.sa | L8: امين يسرى أبو الفتح عبد الو | N8: 93-PZWP-1Y65 | O8: Apple (Refurbished) iPhone 14 Pro Max 5G 128GB - Deep Purple | P8: 1 | Q8: SAR | R8: 2167 | S8: 0 | T8: 12 | U8: 0 | V8: 0 | W8: 0 | X8: Standard | Y8: امين يسرى أبو الفتح عبد الو | Z8: شارع السابع | AA8: 2971 2 | AC8: الخبر | AD8: الشرقية | AE8: EEDE2971 | AF8: SA | AH8: شارع السابع | AI8: 2971 2 | AK8: الخبر | AL8: الشرقية | AM8: EEDE2971 | AN8: SA | AO8: 0 | AP8: -12 | AQ8: AMZSA | AR8: ASA960924789 | AS8: 2025-12-29T20:00:00+03:00 | AT8: JED4 | AU8: AFN | AV8: amazon.sa
A9: 407-1767921-5177960 | C9: U3yt11lmj | D9: D87gp2Z8DZ0xR | E9: 58582345213522 | G9: 2025-12-25T21:07:18+03:00 | H9: 2025-12-26T08:31:52+03:00 | I9: 2025-12-26T08:31:52+03:00 | J9: 2025-12-26T11:32:03+03:00 | K9: hqp481m1j3kwj5s@marketplace.amazon.sa | L9: نوره عبدالله الدوسري | N9: V9-XLU4-MMBG | O9: Apple (Refurbished) iPhone 13 (128GB) - Midnight | P9: 1 | Q9: SAR | R9: 1376 | S9: 0 | T9: 6 | U9: 0 | V9: 0 | W9: 0 | X9: Standard | Y9: نوره عبدالله الدوسري | Z9: النويعمه | AA9: بقالة الجوهرة الاول | AC9: حجلة السواد | AD9: الرياض | AE9: -- | AF9: SA | AH9: النويعمه | AI9: بقالة الجوهرة الاول | AK9: حجلة السواد | AL9: الرياض | AM9: -- | AN9: SA | AO9: 0 | AP9: -6 | AQ9: ARAMEX | AR9: 49883132386 | AS9: 2025-12-29T20:00:00+03:00 | AT9: JED4 | AU9: AFN | AV9: amazon.sa

Sheet Noon KSA
A1: Contract | B1: Business Unit | C1: Document Type | D1: Invoice Type Code | E1: Document Subtype | F1: Document Date | G1: Invoice Nr | H1: Invoice Line Nr | I1: Credit Note Nr | J1: Credit Note Line Nr | K1: Transaction Type | L1: Source Doc Type | M1: Source Doc Nr | N1: Source Doc Line Type | O1: Source Doc Line Nr | P1: check | Q1: Description | R1: SKU | S1: Partner SKU | T1: Misc | U1: Issuer City | V1: Issuer Country | W1: Issuer Location | X1: Receiver City | Y1: Receiver Country | Z1: Receiver Location | AA1: Issuer Legal Entity | AB1: Issuer Legal Name | AC1: Issuer TRN | AD1: Receiver Legal Entity | AE1: Receiver Legal Name | AF1: Receiver TRN | AG1: Document Currency | AH1: VAT Currency | AI1: VAT Rate | AJ1: FX Rate | AK1: Price Excluding VAT (Document Currency) | AL1: Price Excluding VAT (VAT Currency) | AM1: VAT Amount (Document Currency) | AN1: VAT Amount (VAT Currency) | AO1: Price Including VAT (Document Currency)
A2: MPABANGBKLSA | B2: noon | C2: Invoice | D2: nontax_local | E2: Purchase Summary | F2: 46023 | G2: AE2BEHFSH-GSJA000006 | H2: 1 | K2: Customer | L2: Customer order | M2: NSAHC0047226333 | N2: Customer Item | O2: NSAHC0047226333-2-P1 | P2: =VLOOKUP(O2,'Summary Sheet - templete'!F:F,1,0) -> NSAHC0047226333-2-P1 | Q2: Renewed - iPad Pro 2016 (1st Gen) 9.7-Inch 32GB Wi-Fi Space Gray | R2: N70262377V-1 | S2: TABAP032041Max | T2: 70262377 | V2: sa | W2: SA | Y2: sa | Z2: SA | AA2: LE2BEHFSHAE | AB2: Mobisoft Telesolutions FZ-LLC | AC2: 311610579200003 | AE2: بيان السهلي | AG2: SAR | AH2: SAR | AI2: 0 | AJ2: 1 | AK2: 499 | AL2: 499 | AM2: 0 | AN2: 0 | AO2: 499
A3: MPABANGBKLSA | B3: noon | C3: Invoice | D3: nontax_local | E3: Purchase Summary | F3: 46023 | G3: AE2BEHFSH-GSJA000005 | H3: 1 | K3: Customer | L3: Customer order | M3: NSAHC0083560251 | N3: Customer Item | O3: NSAHC0083560251-1-P1 | P3: =VLOOKUP(O3,'Summary Sheet - templete'!F:F,1,0) -> NSAHC0083560251-1-P1 | Q3: Renewed - iPad Pro 2016 (1st Gen) 9.7-Inch 32GB Wi-Fi Space Gray | R3: N70262377V-1 | S3: TABAP032041Max | T3: 11953647581P | V3: sa | W3: SA | Y3: sa | Z3: SA | AA3: LE2BEHFSHAE | AB3: Mobisoft Telesolutions FZ-LLC | AC3: 311610579200003 | AE3: هياء السهلي | AG3: SAR | AH3: SAR | AI3: 0 | AJ3: 1 | AK3: 499 | AL3: 499 | AM3: 0 | AN3: 0 | AO3: 499
A4: MPABANGBKLSA | B4: noon | C4: Invoice | D4: nontax_local | E4: Purchase Summary | F4: 46023 | G4: AE2BEHFSH-GSJA000004 | H4: 1 | K4: Customer | L4: Customer order | M4: NSAHC0047023168 | N4: Customer Item | O4: NSAHC0047023168-1-P1 | P4: =VLOOKUP(O4,'Summary Sheet - templete'!F:F,1,0) -> NSAHC0047023168-1-P1 | Q4: Renewed - iPad Pro 2016 (1st Gen) 9.7-Inch 32GB WiFi Silver | R4: N70262333V-1 | S4: TABAP032039Max | T4: 70262333 | V4: sa | W4: SA | Y4: sa | Z4: SA | AA4: LE2BEHFSHAE | AB4: Mobisoft Telesolutions FZ-LLC | AC4: 311610579200003 | AE4: عيد الحمود | AG4: SAR | AH4: SAR | AI4: 0 | AJ4: 1 | AK4: 449 | AL4: 449 | AM4: 0 | AN4: 0 | AO4: 449
A5: MPABANGBKLSA | B5: noon | C5: Invoice | D5: nontax_local | E5: Purchase Summary | F5: 46023 | G5: AE2BEHFSH-GSJA000003 | H5: 1 | K5: Customer | L5: Customer order | M5: NSAHC0001494244 | N5: Customer Item | O5: NSAHC0001494244-1-P1 | P5: =VLOOKUP(O5,'Summary Sheet - templete'!F:F,1,0) -> NSAHC0001494244-1-P1 | Q5: Renewed - iPhone 14 Pro Max 128GB Deep Purple 5G With Facetime | R5: N70095753V-1 | S5: N70095753V-1 | T5: 70146576 | V5: sa | W5: SA | Y5: sa | Z5: SA | AA5: LE2BEHFSHAE | AB5: Mobisoft Telesolutions FZ-LLC | AC5: 311610579200003 | AE5: Eslamabdalgany الشحات | AG5: SAR | AH5: SAR | AI5: 0 | AJ5: 1 | AK5: 2298 | AL5: 2298 | AM5: 0 | AN5: 0 | AO5: 2298
A6: MPABANGBKLSA | B6: noon | C6: Invoice | D6: nontax_local | E6: Purchase Summary | F6: 46023 | G6: AE2BEHFSH-GSJA000002 | H6: 1 | K6: Customer | L6: Customer order | M6: NSAHC0000707946 | N6: Customer Item | O6: NSAHC0000707946-1-P1 | P6: =VLOOKUP(O6,'Summary Sheet - templete'!F:F,1,0) -> NSAHC0000707946-1-P1 | Q6: Renewed - iPhone 14 Pro 256GB Deep Purple 5G With Facetime - International Version | R6: N53431294A | S6: N53431294A-1 | T6: 70146560 | V6: sa | W6: SA | Y6: sa | Z6: SA | AA6: LE2BEHFSHAE | AB6: Mobisoft Telesolutions FZ-LLC | AC6: 311610579200003 | AE6: Rojim Sk | AG6: SAR | AH6: SAR | AI6: 0 | AJ6: 1 | AK6: 2262 | AL6: 2262 | AM6: 0 | AN6: 0 | AO6: 2262
A7: MPABANGBKLSA | B7: noon | C7: Invoice | D7: nontax_local | E7: Purchase Summary | F7: 46023 | G7: AE2BEHFSH-GSJA000001 | H7: 1 | K7: Customer | L7: Customer order | M7: NSAHC0082879023 | N7: Customer Item | O7: NSAHC0082879023-1-P1 | P7: =VLOOKUP(O7,'Summary Sheet - templete'!F:F,1,0) -> NSAHC0082879023-1-P1 | Q7: Renewed - iPad Pro 2016 (1st Gen) 9.7-Inch 32GB WiFi Silver | R7: N70262333V-1 | S7: TABAP032039Max | T7: 70262333 | V7: sa | W7: SA | Y7: sa | Z7: SA | AA7: LE2BEHFSHAE | AB7: Mobisoft Telesolutions FZ-LLC | AC7: 311610579200003 | AE7: سعود الودعاني | AG7: SAR | AH7: SAR | AI7: 0 | AJ7: 1 | AK7: 449 | AL7: 449 | AM7: 0 | AN7: 0 | AO7: 449
A8: MPABANGBKLSA | B8: noon | C8: Invoice | D8: nontax_local | E8: Purchase Summary | F8: 46022 | G8: AE2BEHFSH-GSIL000076 | H8: 1 | K8: Customer | L8: Customer order | M8: NSAHC0013207023 | N8: Customer Item | O8: NSAHC0013207023-1-P1 | P8: =VLOOKUP(O8,'Summary Sheet - templete'!F:F,1,0) -> NSAHC0013207023-1-P1 | Q8: Renewed - iPad 2018 (6th Gen) 9.7-Inch 32GB Wi-Fi Space Grey - International Version | R8: N53382311A | S8: N53382311A | T8: GG7WXLMEJF8J | V8: sa | W8: SA | Y8: sa | Z8: SA | AA8: LE2BEHFSHAE | AB8: Mobisoft Telesolutions FZ-LLC | AC8: 311610579200003 | AE8: md shahabuddin | AG8: SAR | AH8: SAR | AI8: 0 | AJ8: 1 | AK8: 398 | AL8: 398 | AM8: 0 | AN8: 0 | AO8: 398
A9: MPABANGBKLSA | B9: noon | C9: Invoice | D9: nontax_local | E9: Purchase Summary | F9: 46022 | G9: AE2BEHFSH-GSIL000075 | H9: 1 | K9: Customer | L9: Customer order | M9: NSAHC0053527539 | N9: Customer Item | O9: NSAHC0053527539-1-P1 | P9: =VLOOKUP(O9,'Summary Sheet - templete'!F:F,1,0) -> NSAHC0053527539-1-P1 | Q9: Renewed - iPad Pro 2020 (4th Gen) 12.9-inch 512GB Wi-Fi 4G LTE Space Gray With FaceTime | R9: N51142274A | S9: N51142274A | T9: 51142274 | V9: sa | W9: SA | Y9: sa | Z9: SA | AA9: LE2BEHFSHAE | AB9: Mobisoft Telesolutions FZ-LLC | AC9: 311610579200003 | AE9: eduard barbosa | AG9: SAR | AH9: SAR | AI9: 0 | AJ9: 1 | AK9: 2599 | AL9: 2599 | AM9: 0 | AN9: 0 | AO9: 2599
A10: MPABANGBKLSA | B10: noon | C10: Creditnote | D10: nontax_local | E10: Purchase Return Summary | F10: 46022 | G10: AE2BEHFSH-GSIL000069 | H10: 1 | I10: AE2BEHFSH-DSIL000028 | J10: 1 | K10: Customer | L10: Customer order | M10: NSAHC0002594656 | N10: Customer Item | O10: NSAHC0002594656-2-P1 | P10: =VLOOKUP(O10,'Summary Sheet - templete'!F:F,1,0) -> NSAHC0002594656-2-P1 | Q10: Renewed - iPad 2018 (6th Gen) 9.7-Inch 32GB Wi-Fi Space Grey - International Version | R10: N53382311A | S10: N53382311A | T10: GG7WXLMEJF8J | V10: sa | W10: SA | Y10: sa | Z10: SA | AA10: LE2BEHFSHAE | AB10: Mobisoft Telesolutions FZ-LLC | AC10: 311610579200003 | AE10: سلطان العتيبي | AG10: SAR | AH10: SAR | AI10: 0 | AJ10: 1 | AK10: 398 | AL10: 398 | AM10: 0 | AN10: 0 | AO10: 398
A11: MPABANGBKLSA | B11: noon | C11: Invoice | D11: nontax_local | E11: Purchase Summary | F11: 46021 | G11: AE2BEHFSH-GSIL000074 | H11: 1 | K11: Customer | L11: Customer order | M11: NSAHC0017132006 | N11: Customer Item | O11: NSAHC0017132006-2-P1 | P11: =VLOOKUP(O11,'Summary Sheet - templete'!F:F,1,0) -> NSAHC0017132006-2-P1 | Q11: Renewed - iPad-2019 (7th Gen) 10.2inch 32GB Wi-Fi 4G LTE Silver - International Version | R11: N50388287A | S11: N50388287A | T11: 353212105700763 | V11: sa | W11: SA | Y11: sa | Z11: SA | AA11: LE2BEHFSHAE | AB11: Mobisoft Telesolutions FZ-LLC | AC11: 311610579200003 | AE11: saad alotabi | AG11: SAR | AH11: SAR | AI11: 0 | AJ11: 1 | AK11: 524 | AL11: 524 | AM11: 0 | AN11: 0 | AO11: 524
A12: MPABANGBKLSA | B12: noon | C12: Invoice | D12: nontax_local | E12: Purchase Summary | F12: 46020 | G12: AE2BEHFSH-GSIL000073 | H12: 1 | K12: Customer | L12: Customer order | M12: NSAHC0007179996 | N12: Customer Item | O12: NSAHC0007179996-2-P1 | P12: =VLOOKUP(O12,'Summary Sheet - templete'!F:F,1,0) -> NSAHC0007179996-2-P1 | Q12: Renewed - iPad Pro 2021 5th Generation 12.9-Inch, M1 Chip, 512GB, Wi-Fi, 5G, Silver with Facetime - International Specs | R12: N70210242V-1 | S12: N46875147A | T12: 11557662100P | V12: sa | W12: SA | Y12: sa | Z12: SA | AA12: LE2BEHFSHAE | AB12: Mobisoft Telesolutions FZ-LLC | AC12: 311610579200003 | AE12: abdulmohsen alammar | AG12: SAR | AH12: SAR | AI12: 0 | AJ12: 1 | AK12: 3189 | AL12: 3189 | AM12: 0 | AN12: 0 | AO12: 3189
A13: MPABANGBKLSA | B13: noon | C13: Invoice | D13: nontax_local | E13: Purchase Summary | F13: 46020 | G13: AE2BEHFSH-GSIL000072 | H13: 1 | K13: Customer | L13: Customer order | M13: NSAHC0088492440 | N13: Customer Item | O13: NSAHC0088492440-1-P1 | P13: =VLOOKUP(O13,'Summary Sheet - templete'!F:F,1,0) -> NSAHC0088492440-1-P1 | Q13: Renewed - iPad-2019 (7th Gen) 10.2inch 32GB Wi-Fi 4G LTE Silver - International Version | R13: N50388287A | S13: N50388287A | T13: 353212105596195 | V13: sa | W13: SA | Y13: sa | Z13: SA | AA13: LE2BEHFSHAE | AB13: Mobisoft Telesolutions FZ-LLC | AC13: 311610579200003 | AE13: شريفه القحطاني | AG13: SAR | AH13: SAR | AI13: 0 | AJ13: 1 | AK13: 524 | AL13: 524 | AM13: 0 | AN13: 0 | AO13: 524
A14: MPABANGBKLSA | B14: noon | C14: Invoice | D14: nontax_local | E14: Purchase Summary | F14: 46020 | G14: AE2BEHFSH-GSIL000071 | H14: 1 | K14: Customer | L14: Customer order | M14: NSAHC0084762122 | N14: Customer Item | O14: NSAHC0084762122-1-P1 | P14: =VLOOKUP(O14,'Summary Sheet - templete'!F:F,1,0) -> NSAHC0084762122-1-P1 | Q14: Renewed - iPad 2017 (5th Gen) 9.7inch 32GBWiFi Space Gray With Facetime | R14: N34261427A | S14: N34261427A | T14: 34261427 | V14: sa | W14: SA | Y14: sa | Z14: SA | AA14: LE2BEHFSHAE | AB14: Mobisoft Telesolutions FZ-LLC | AC14: 311610579200003 | AE14: ام بتال | AG14: SAR | AH14: SAR | AI14: 0 | AJ14: 1 | AK14: 429 | AL14: 429 | AM14: 0 | AN14: 0 | AO14: 429
A15: MPABANGBKLSA | B15: noon | C15: Invoice | D15: nontax_local | E15: Purchase Summary | F15: 46020 | G15: AE2BEHFSH-GSIL000071 | H15: 2 | K15: Customer | L15: Customer order | M15: NSAHC0084762122 | N15: Customer Item | O15: NSAHC0084762122-2-P1 | P15: =VLOOKUP(O15,'Summary Sheet - templete'!F:F,1,0) -> NSAHC0084762122-2-P1 | Q15: Renewed - iPad 2018 (6th Gen) 9.7-Inch 32GB Wi-Fi Space Grey - International Version | R15: N53382311A | S15: N53382311A | T15: 53382311 | V15: sa | W15: SA | Y15: sa | Z15: SA | AA15: LE2BEHFSHAE | AB15: Mobisoft Telesolutions FZ-LLC | AC15: 311610579200003 | AE15: ام بتال | AG15: SAR | AH15: SAR | AI15: 0 | AJ15: 1 | AK15: 398 | AL15: 398 | AM15: 0 | AN15: 0 | AO15: 398
A16: MPABANGBKLSA | B16: noon | C16: Invoice | D16: nontax_local | E16: Purchase Summary | F16: 46020 | G16: AE2BEHFSH-GSIL000070 | H16: 1 | K16: Customer | L16: Customer order | M16: NSAHC0085871396 | N16: Customer Item | O16: NSAHC0085871396-1-P1 | P16: =VLOOKUP(O16,'Summary Sheet - templete'!F:F,1,0) -> NSAHC0085871396-1-P1 | Q16: Renewed – iPad Pro 11-Inch (2018) 1st Gen WiFi + Cellular 256GB Space Gray | R16: N70259511V-1 | S16: TABAP256035 | T16: 70259511 | V16: sa | W16: SA | Y16: sa | Z16: SA | AA16: LE2BEHFSHAE | AB16: Mobisoft Telesolutions FZ-LLC | AC16: 311610579200003 | AE16: Sunil Lama | AG16: SAR | AH16: SAR | AI16: 0 | AJ16: 1 | AK16: 1649 | AL16: 1649 | AM16: 0 | AN16: 0 | AO16: 1649
A17: MPABANGBKLSA | B17: noon | C17: Invoice | D17: nontax_local | E17: Purchase Summary | F17: 46020 | G17: AE2BEHFSH-GSIL000069 | H17: 1 | K17: Customer | L17: Customer order | M17: NSAHC0002594656 | N17: Customer Item | O17: NSAHC0002594656-2-P1 | P17: =VLOOKUP(O17,'Summary Sheet - templete'!F:F,1,0) -> NSAHC0002594656-2-P1 | Q17: Renewed - iPad 2018 (6th Gen) 9.7-Inch 32GB Wi-Fi Space Grey - International Version | R17: N53382311A | S17: N53382311A | T17: GG7WXLMEJF8J | V17: sa | W17: SA | Y17: sa | Z17: SA | AA17: LE2BEHFSHAE | AB17: Mobisoft Telesolutions FZ-LLC | AC17: 311610579200003 | AE17: سلطان العتيبي | AG17: SAR | AH17: SAR | AI17: 0 | AJ17: 1 | AK17: 398 | AL17: 398 | AM17: 0 | AN17: 0 | AO17: 398
A18: MPABANGBKLSA | B18: noon | C18: Invoice | D18: nontax_local | E18: Purchase Summary | F18: 46020 | G18: AE2BEHFSH-GSIL000068 | H18: 1 | K18: Customer | L18: Customer order | M18: NSAHC0047546591 | N18: Customer Item | O18: NSAHC0047546591-1-P1 | P18: =VLOOKUP(O18,'Summary Sheet - templete'!F:F,1,0) -> NSAHC0047546591-1-P1 | Q18: Renewed - iPad 2018 (6th Gen) 9.7-Inch 32GB Wi-Fi Space Grey - International Version | R18: N53382311A | S18: N53382311A | T18: 53382311 | V18: sa | W18: SA | Y18: sa | Z18: SA | AA18: LE2BEHFSHAE | AB18: Mobisoft Telesolutions FZ-LLC | AC18: 311610579200003 | AE18: عبدالرحمن ال عتيق | AG18: SAR | AH18: SAR | AI18: 0 | AJ18: 1 | AK18: 398 | AL18: 398 | AM18: 0 | AN18: 0 | AO18: 398
A19: MPABANGBKLSA | B19: noon | C19: Invoice | D19: nontax_local | E19: Purchase Summary | F19: 46020 | G19: AE2BEHFSH-GSIL000067 | H19: 1 | K19: Customer | L19: Customer order | M19: NSAHC0032889994 | N19: Customer Item | O19: NSAHC0032889994-1-P1 | P19: =VLOOKUP(O19,'Summary Sheet - templete'!F:F,1,0) -> NSAHC0032889994-1-P1 | Q19: Renewed - iPad 2018 (6th Gen) 9.7-Inch 32GB Wi-Fi Space Grey - International Version | R19: N53382311A | S19: N53382311A | T19: 53382311 | V19: sa | W19: SA | Y19: sa | Z19: SA | AA19: LE2BEHFSHAE | AB19: Mobisoft Telesolutions FZ-LLC | AC19: 311610579200003 | AE19: امل الشهري | AG19: SAR | AH19: SAR | AI19: 0 | AJ19: 1 | AK19: 398 | AL19: 398 | AM19: 0 | AN19: 0 | AO19: 398
A20: MPABANGBKLSA | B20: noon | C20: Invoice | D20: nontax_local | E20: Purchase Summary | F20: 46019 | G20: AE2BEHFSH-GSIL000066 | H20: 1 | K20: Customer | L20: Customer order | M20: NSAHC0082186765 | N20: Customer Item | O20: NSAHC0082186765-2-P1 | P20: =VLOOKUP(O20,'Summary Sheet - templete'!F:F,1,0) -> NSAHC0082186765-2-P1 | Q20: Renewed - Ipad 2019 (7th Gen) 10.2-Inch 128GB Wi-Fi,LTE, Space Gray - International Version | R20: N70210253V-1 | S20: N37936028ALTE | T20: 353212106168796 | V20: sa | W20: SA | Y20: sa | Z20: SA | AA20: LE2BEHFSHAE | AB20: Mobisoft Telesolutions FZ-LLC | AC20: 311610579200003 | AE20: امير ابراهيم | AG20: SAR | AH20: SAR | AI20: 0 | AJ20: 1 | AK20: 699 | AL20: 699 | AM20: 0 | AN20: 0 | AO20: 699
A21: MPABANGBKLSA | B21: noon | C21: Invoice | D21: nontax_local | E21: Purchase Summary | F21: 46019 | G21: AE2BEHFSH-GSIL000065 | H21: 1 | K21: Customer | L21: Customer order | M21: NSAHC0065081485 | N21: Customer Item | O21: NSAHC0065081485-3-P1 | P21: =VLOOKUP(O21,'Summary Sheet - templete'!F:F,1,0) -> NSAHC0065081485-3-P1 | Q21: Renewed - iPad Air 2 9.7inch 32GB Wi-Fi Space Gray With FaceTime | R21: N53408690A | S21: N53408690A | T21: BEYOND10450 | V21: sa | W21: SA | Y21: sa | Z21: SA | AA21: LE2BEHFSHAE | AB21: Mobisoft Telesolutions FZ-LLC | AC21: 311610579200003 | AE21: ناديه الميزاني | AG21: SAR | AH21: SAR | AI21: 0 | AJ21: 1 | AK21: 399 | AL21: 399 | AM21: 0 | AN21: 0 | AO21: 399
A22: MPABANGBKLSA | B22: noon | C22: Invoice | D22: nontax_local | E22: Purchase Summary | F22: 46019 | G22: AE2BEHFSH-GSIL000064 | H22: 1 | K22: Customer | L22: Customer order | M22: NSAHC0010472664 | N22: Customer Item | O22: NSAHC0010472664-1-P1 | P22: =VLOOKUP(O22,'Summary Sheet - templete'!F:F,1,0) -> NSAHC0010472664-1-P1 | Q22: Renewed - iPad 2017 (5th Gen) 9.7inch 32GBWiFi Space Gray With Facetime | R22: N34261427A | S22: N34261427A | T22: GCHV40RPHLF9 | V22: sa | W22: SA | Y22: sa | Z22: SA | AA22: LE2BEHFSHAE | AB22: Mobisoft Telesolutions FZ-LLC | AC22: 311610579200003 | AE22: رحاب الشمراني | AG22: SAR | AH22: SAR | AI22: 0 | AJ22: 1 | AK22: 429 | AL22: 429 | AM22: 0 | AN22: 0 | AO22: 429
A23: MPABANGBKLSA | B23: noon | C23: Invoice | D23: nontax_local | E23: Purchase Summary | F23: 46019 | G23: AE2BEHFSH-GSIL000063 | H23: 1 | K23: Customer | L23: Customer order | M23: NSAHC0064138549 | N23: Customer Item | O23: NSAHC0064138549-1-P1 | P23: =VLOOKUP(O23,'Summary Sheet - templete'!F:F,1,0) -> NSAHC0064138549-1-P1 | Q23: Renewed - iPad 2017 (5th Gen) 9.7inch 32GBWiFi Space Gray With Facetime | R23: N34261427A | S23: N34261427A | T23: F9GTK57VHLF9 | V23: sa | W23: SA | Y23: sa | Z23: SA | AA23: LE2BEHFSHAE | AB23: Mobisoft Telesolutions FZ-LLC | AC23: 311610579200003 | AE23: ملهيه الشويلعي | AG23: SAR | AH23: SAR | AI23: 0 | AJ23: 1 | AK23: 429 | AL23: 429 | AM23: 0 | AN23: 0 | AO23: 429
A24: MPABANGBKLSA | B24: noon | C24: Invoice | D24: nontax_local | E24: Purchase Summary | F24: 46019 | G24: AE2BEHFSH-GSIL000062 | H24: 1 | K24: Customer | L24: Customer order | M24: NSAHC0080314615 | N24: Customer Item | O24: NSAHC0080314615-1-P1 | P24: =VLOOKUP(O24,'Summary Sheet - templete'!F:F,1,0) -> NSAHC0080314615-1-P1 | Q24: Renewed - iPad Air 2 9.7inch 32GB Wi-Fi Space Gray With FaceTime | R24: N53408690A | S24: N53408690A | T24: 53408690 | V24: sa | W24: SA | Y24: sa | Z24: SA | AA24: LE2BEHFSHAE | AB24: Mobisoft Telesolutions FZ-LLC | AC24: 311610579200003 | AE24: هديل محمد | AG24: SAR | AH24: SAR | AI24: 0 | AJ24: 1 | AK24: 399 | AL24: 399 | AM24: 0 | AN24: 0 | AO24: 399
A25: MPABANGBKLSA | B25: noon | C25: Creditnote | D25: nontax_local | E25: Purchase Return Summary | F25: 46019 | G25: AE2BEHFSH-GSIL000058 | H25: 1 | I25: AE2BEHFSH-DSIL000026 | J25: 1 | K25: Customer | L25: Customer order | M25: NSAHC0081508707 | N25: Customer Item | O25: NSAHC0081508707-1-P1 | P25: =VLOOKUP(O25,'Summary Sheet - templete'!F:F,1,0) -> NSAHC0081508707-1-P1 | Q25: Renewed - Ipad 2019 (7th Gen) 10.2-Inch 128GB Wi-Fi,LTE, Space Gray - International Version | R25: N70210253V-1 | S25: N37936028ALTE | T25: 353212106168796 | V25: sa | W25: SA | Y25: sa | Z25: SA | AA25: LE2BEHFSHAE | AB25: Mobisoft Telesolutions FZ-LLC | AC25: 311610579200003 | AE25: Muhammad Muhammad | AG25: SAR | AH25: SAR | AI25: 0 | AJ25: 1 | AK25: 599 | AL25: 599 | AM25: 0 | AN25: 0 | AO25: 599
A26: MPABANGBKLSA | B26: noon | C26: Creditnote | D26: nontax_local | E26: Purchase Return Summary | F26: 46019 | G26: AE2BEHFSH-GSIL000055 | H26: 1 | I26: AE2BEHFSH-DSIL000025 | J26: 1 | K26: Customer | L26: Customer order | M26: NSAHC0091664187 | N26: Customer Item | O26: NSAHC0091664187-1-P1 | P26: =VLOOKUP(O26,'Summary Sheet - templete'!F:F,1,0) -> NSAHC0091664187-1-P1 | Q26: Renewed - iPhone 14 Pro Max 128GB Deep Purple 5G With Facetime | R26: N70095753V-1 | S26: N70095753V-1 | T26: 355822265951518 | V26: sa | W26: SA | Y26: sa | Z26: SA | AA26: LE2BEHFSHAE | AB26: Mobisoft Telesolutions FZ-LLC | AC26: 311610579200003 | AE26: علاءالدين عبدالقادر | AG26: SAR | AH26: SAR | AI26: 0 | AJ26: 1 | AK26: 2399 | AL26: 2399 | AM26: 0 | AN26: 0 | AO26: 2399
A27: MPABANGBKLSA | B27: noon | C27: Invoice | D27: nontax_local | E27: Purchase Summary | F27: 46018 | G27: AE2BEHFSH-GSIL000061 | H27: 1 | K27: Customer | L27: Customer order | M27: NSAHC0037327791 | N27: Customer Item | O27: NSAHC0037327791-4-P1 | P27: =VLOOKUP(O27,'Summary Sheet - templete'!F:F,1,0) -> NSAHC0037327791-4-P1 | Q27: Renewed - Ipad 2019 (7th Gen) 10.2-Inch 128GB Wi-Fi,LTE, Space Gray - International Version | R27: N70210253V-1 | S27: N37936028ALTE | T27: 353210104634363 | V27: sa | W27: SA | Y27: sa | Z27: SA | AA27: LE2BEHFSHAE | AB27: Mobisoft Telesolutions FZ-LLC | AC27: 311610579200003 | AE27: Anelyn Tajon | AG27: SAR | AH27: SAR | AI27: 0 | AJ27: 1 | AK27: 699 | AL27: 699 | AM27: 0 | AN27: 0 | AO27: 699
A28: MPABANGBKLSA | B28: noon | C28: Invoice | D28: nontax_local | E28: Purchase Summary | F28: 46018 | G28: AE2BEHFSH-GSIL000060 | H28: 1 | K28: Customer | L28: Customer order | M28: NSAHC0063312130 | N28: Customer Item | O28: NSAHC0063312130-2-P1 | P28: =VLOOKUP(O28,'Summary Sheet - templete'!F:F,1,0) -> NSAHC0063312130-2-P1 | Q28: Renewed - Ipad 2019 (7th Gen) 10.2-Inch 128GB Wi-Fi,LTE, Space Gray - International Version | R28: N70210253V-1 | S28: N37936028ALTE | T28: 353209105408033 | V28: sa | W28: SA | Y28: sa | Z28: SA | AA28: LE2BEHFSHAE | AB28: Mobisoft Telesolutions FZ-LLC | AC28: 311610579200003 | AE28: Ronald Pantua | AG28: SAR | AH28: SAR | AI28: 0 | AJ28: 1 | AK28: 599 | AL28: 599 | AM28: 0 | AN28: 0 | AO28: 599
